revcorml/__init__.py
revcorml/proise.py
revcorml-0.2.dist-info/METADATA
revcorml-0.2.dist-info/WHEEL
revcorml-0.2.dist-info/top_level.txt
revcorml-0.2.dist-info/RECORD
