Metadata-Version: 2.1
Name: revcorml
Version: 0.2
Summary: tools to probe machine learning classifiers with noise, bubbles and reverse correlation
Home-page: https://github.com/EtienneTho/revcorml
Author: Etienne Thoret, Thomas Andrillon, Damien Léger, Daniel Pressnitzer
Author-email: etienne.thoret@univ-amu.fr
License: MIT
Download-URL: https://github.com/EtienneTho/revcorml/blob/main/dist/revcorml-0.2.tar.gz
Platform: UNKNOWN
Requires-Dist: numpy
Requires-Dist: sklearn
Requires-Dist: scipy
